pytdb
