Metadata-Version: 1.0
Name: pytdb
Version: 0.0.2
Summary: Very fast and simple time series db, tightly integrated with Python and Pandas.
Home-page: https://github.com/PiotrDabkowski/pytdb
Author: Piotr Dabkowski
Author-email: UNKNOWN
License: UNKNOWN
Platform: UNKNOWN
